seebuoy/__init__.py
seebuoy/ndbc/__init__.py
seebuoy/ndbc/current_year.py
seebuoy/ndbc/data/large_cities.py
seebuoy/ndbc/extract.py
seebuoy/ndbc/historical.py
seebuoy/ndbc/metadata.py
seebuoy/ndbc/ndbc.py
seebuoy/ndbc/real_time.py
seebuoy/ndbc/utils.py
seebuoy/ww3/__init__.py
seebuoy/ww3/forecast.py
seebuoy-0.2.2.dist-info/WHEEL
seebuoy-0.2.2.dist-info/LICENSE
seebuoy-0.2.2.dist-info/METADATA
seebuoy-0.2.2.dist-info/RECORD
